hathitables.py
setup.py
hathitables.egg-info/PKG-INFO
hathitables.egg-info/SOURCES.txt
hathitables.egg-info/dependency_links.txt
hathitables.egg-info/requires.txt
hathitables.egg-info/top_level.txt