Metadata-Version: 1.0
Name: hathitables
Version: 0.0.1
Summary: Turn HathiTrust Collections into CSV
Home-page: http://github.com/umd_mith/hathitables
Author: Ed Summers
Author-email: ehs@pobox.com
License: UNKNOWN
Platform: UNKNOWN
